benderopt/__init__.py
benderopt/minimizer.py
benderopt/rng.py
benderopt/utils.py
benderopt/base/__init__.py
benderopt/base/observation.py
benderopt/base/optimization_problem.py
benderopt/base/parameter.py
benderopt/optimizer/__init__.py
benderopt/optimizer/optimizer.py
benderopt/optimizer/parzen_estimator.py
benderopt/optimizer/random.py
benderopt/stats/__init__.py
benderopt/stats/categorical.py
benderopt/stats/lognormal.py
benderopt/stats/loguniform.py
benderopt/stats/mixture.py
benderopt/stats/normal.py
benderopt/stats/uniform.py
benderopt/validation/__init__.py
benderopt/validation/categorical.py
benderopt/validation/lognormal.py
benderopt/validation/loguniform.py
benderopt/validation/mixture.py
benderopt/validation/normal.py
benderopt/validation/uniform.py
benderopt/validation/utils.py
benderopt-1.4.2.dist-info/LICENSE
benderopt-1.4.2.dist-info/METADATA
benderopt-1.4.2.dist-info/WHEEL
benderopt-1.4.2.dist-info/top_level.txt
benderopt-1.4.2.dist-info/RECORD
