Metadata-Version: 2.1
Name: benderopt
Version: 1.4.2
Summary: Black Box optimization library.
Home-page: https://github.com/Dreem-Organization/benderopt
Author: Valentin Thorey
Author-email: v.thorey@gmail.com
Classifier: Programming Language :: Python
Classifier: Programming Language :: Python :: 3
License-File: LICENSE
Requires-Dist: numpy >=1.15.4
Requires-Dist: scipy >=1.1.0
Provides-Extra: dev
Requires-Dist: black ; extra == 'dev'
Requires-Dist: isort ; extra == 'dev'
Provides-Extra: test
Requires-Dist: pytest ; extra == 'test'
Requires-Dist: pytest-coverage ; extra == 'test'
